twitter_amnesia/__init__.py
twitter_amnesia/arg_parsing.py
twitter_amnesia/helpers.py
twitter_amnesia/main.py
twitter_amnesia-1.1.3.dist-info/LICENSE
twitter_amnesia-1.1.3.dist-info/METADATA
twitter_amnesia-1.1.3.dist-info/WHEEL
twitter_amnesia-1.1.3.dist-info/entry_points.txt
twitter_amnesia-1.1.3.dist-info/top_level.txt
twitter_amnesia-1.1.3.dist-info/RECORD
