Metadata-Version: 2.1
Name: twitter-amnesia
Version: 1.1.3
Summary: A twitter service used to delete tweets not protected by a custom tag and older than a specific date.
Home-page: UNKNOWN
Author: Carlos Miguel Ferreira
Author-email: carlosmf.pt@gmail.com
Maintainer: Carlos Miguel Ferreira
Maintainer-email: carlosmf.pt@gmail.com
License: GPLv3
Keywords: Twitter,Management
Platform: UNKNOWN
Classifier: Development Status :: 5 - Production/Stable
Classifier: License :: OSI Approved :: GNU General Public License v3 (GPLv3)
Classifier: Programming Language :: Python :: 3 :: Only
Classifier: Programming Language :: Python :: 3.8
Requires-Dist: python-twitter (==3.5)
Requires-Dist: python-dateutil (==2.8.1)
